__init__.py
picezim.py
picezim-0.4.0.dist-info/licenses/LICENSE
picezim-0.4.0.dist-info/METADATA
picezim-0.4.0.dist-info/WHEEL
picezim-0.4.0.dist-info/top_level.txt
picezim-0.4.0.dist-info/RECORD
