Metadata-Version: 2.4
Name: picezim
Version: 0.4.0
Summary: A short description of your package
Author-email: Qendrim Krasniqi <qendrim.krasniqi.ext@karlstorz.com>
Project-URL: Homepage, https://github.com/yourusername/your-package
Requires-Python: >=3.7
License-File: LICENSE
Dynamic: license-file
